fastrustrag-0.1.2.dist-info/METADATA
fastrustrag-0.1.2.dist-info/WHEEL
fastrustrag-0.1.2.dist-info/licenses/LICENSE
fastrustrag/__init__.py
fastrustrag/fastrustrag.cpython-312-darwin.so
fastrustrag-0.1.2.dist-info/RECORD
