Metadata-Version: 2.4
Name: fastrustrag
Version: 0.1.2
Classifier: Development Status :: 4 - Beta
Classifier: Intended Audience :: Developers
Classifier: Intended Audience :: Science/Research
Classifier: License :: OSI Approved :: MIT License
Classifier: Programming Language :: Python :: 3
Classifier: Programming Language :: Python :: 3.8
Classifier: Programming Language :: Python :: 3.9
Classifier: Programming Language :: Python :: 3.10
Classifier: Programming Language :: Python :: 3.11
Classifier: Programming Language :: Python :: 3.12
Classifier: Programming Language :: Rust
Classifier: Topic :: Scientific/Engineering :: Artificial Intelligence
Classifier: Topic :: Software Development :: Libraries :: Python Modules
License-File: LICENSE
Summary: FastRustRAG: Blazing-fast document deduplication using MinHash and LSH - 50-100x faster than Python
Keywords: minhash,lsh,deduplication,rag,rust,preprocessing
Author-email: Manoj Krishna Mohan <mnjkshrm@gmail.com>
License: MIT
Requires-Python: >=3.8
